groclake-0.6.1-py3.9-nspkg.pth
groclake/config.py
groclake/actionlake/__init__.py
groclake/actionlake/actionlake.py
groclake/agentlake/__init__.py
groclake/agentlake/agentlake.py
groclake/cataloglake/__init__.py
groclake/cataloglake/cataloglake.py
groclake/cloudlake/__init__.py
groclake/cloudlake/cloudlake.py
groclake/commlake/__init__.py
groclake/commlake/commlake.py
groclake/datalake/__init__.py
groclake/datalake/connection.py
groclake/datalake/datalake.py
groclake/datalake/pipeline.py
groclake/datalake/transformations.py
groclake/deviationlake/__init__.py
groclake/deviationlake/deviationlake.py
groclake/issuelake/__init__.py
groclake/issuelake/issuelake.py
groclake/joblake/__init__.py
groclake/joblake/joblake.py
groclake/knowledgelake/__init__.py
groclake/knowledgelake/knowledgelake.py
groclake/memorylake/__init__.py
groclake/memorylake/memorylake.py
groclake/mllake/__init__.py
groclake/mllake/anomaly_detection.py
groclake/mllake/classification.py
groclake/mllake/clustering.py
groclake/mllake/dimensionality_reduction.py
groclake/mllake/feature_selection.py
groclake/mllake/regression.py
groclake/mllake/statistics.py
groclake/modellake/__init__.py
groclake/modellake/modellake.py
groclake/monitorlake/__init__.py
groclake/monitorlake/monitorlake.py
groclake/observationlake/__init__.py
groclake/observationlake/observationlake.py
groclake/promptlake/__init__.py
groclake/promptlake/promptlake.py
groclake/rcalake/__init__.py
groclake/rcalake/rcalake.py
groclake/remediationlake/__init__.py
groclake/remediationlake/remediationlake.py
groclake/resumelake/__init__.py
groclake/resumelake/resumelake.py
groclake/thresholdlake/__init__.py
groclake/thresholdlake/thresholdlake.py
groclake/toollake/__init__.py
groclake/toollake/auth_gateway.py
groclake/toollake/analytics/__init__.py
groclake/toollake/analytics/powerbi.py
groclake/toollake/analytics/tableau.py
groclake/toollake/apm/__init__.py
groclake/toollake/apm/appdynamics.py
groclake/toollake/apm/datadog.py
groclake-0.6.1.dist-info/METADATA
groclake-0.6.1.dist-info/WHEEL
groclake-0.6.1.dist-info/namespace_packages.txt
groclake-0.6.1.dist-info/top_level.txt
groclake-0.6.1.dist-info/RECORD
