Metadata-Version: 2.4
Name: groclake
Version: 0.6.1
Requires-Dist: requests
Requires-Dist: mysql-connector-python
Requires-Dist: redis
Requires-Dist: elasticsearch<9.0.0,>=8.11.0
Requires-Dist: google-cloud-storage
Requires-Dist: Pillow
Requires-Dist: boto3
Requires-Dist: pymongo
Requires-Dist: PyPDF2
Requires-Dist: markdownify
Requires-Dist: python-docx
Requires-Dist: google-genai
Requires-Dist: openai
Requires-Dist: anthropic
Requires-Dist: google-generativeai
Requires-Dist: groq
Requires-Dist: pytz
Requires-Dist: python-dotenv
Requires-Dist: notion-client
Requires-Dist: pypdf
Requires-Dist: snowflake-connector-python
Requires-Dist: slack-sdk
Requires-Dist: jira
Requires-Dist: simple-salesforce
Requires-Dist: neo4j
Requires-Dist: python-magic
Requires-Dist: python-pptx
Requires-Dist: python-docx
Requires-Dist: pymupdf
Requires-Dist: reportlab
Requires-Dist: xlrd
Requires-Dist: tableauhyperapi
Requires-Dist: pandas
Requires-Dist: requests-toolbelt
Requires-Dist: google-auth-oauthlib
Requires-Dist: google-api-python-client
Requires-Dist: google-auth
Requires-Dist: google-cloud-compute
Requires-Dist: google-cloud-redis
Requires-Dist: google-cloud-storage
Requires-Dist: google-api-python-client
Requires-Dist: tiktoken
Requires-Dist: hubspot-api-client
Requires-Dist: scikit-learn
Requires-Dist: xgboost
Requires-Dist: matplotlib
Requires-Dist: numpy
Requires-Dist: scikit-learn
Requires-Dist: schedule
Requires-Dist: croniter
Dynamic: requires-dist
